GeneticPromptLab/__init__.py
GeneticPromptLab/base_class.py
GeneticPromptLab/function_templates.py
GeneticPromptLab/qa_optim.py
GeneticPromptLab/utils.py
genetic_prompt_lab-1.0.1.dist-info/LICENSE
genetic_prompt_lab-1.0.1.dist-info/METADATA
genetic_prompt_lab-1.0.1.dist-info/WHEEL
genetic_prompt_lab-1.0.1.dist-info/top_level.txt
genetic_prompt_lab-1.0.1.dist-info/RECORD
