Metadata-Version: 2.1
Name: genetic-prompt-lab
Version: 1.0.1
Summary: GeneticPromptLab uses genetic algorithms for automated prompt engineering (for LLMs), enhancing quality and diversity through iterative selection, crossover, and mutation, while efficiently exploring minimal yet diverse samples from the training set.
Home-page: http://github.com/AmanPriyanshu/GeneticPromptLab
Author: Aman Priyanshu and Supriti Vijay
Author-email: amanpriyanshusms2001@gmail.com
License: MIT
Keywords: llm llms prompt-optimization prompt-engineering genetic-algorithms automated-prompt-generation evolutionary-algorithms evolutionary-algorithm prompt-mutation prompt-crossover AI-optimization prompt prompts prompt-tuning prompt-engineering-tools LLM-enhancements
Classifier: Development Status :: 3 - Alpha
Classifier: Intended Audience :: Developers
Classifier: License :: OSI Approved :: MIT License
Classifier: Programming Language :: Python :: 3
License-File: LICENSE
Requires-Dist: pandas ==2.2.2
Requires-Dist: scikit-learn ==1.5.0
Requires-Dist: scipy ==1.13.1
Requires-Dist: sentence-transformers ==3.0.1
Requires-Dist: setuptools ==70.1.0
Requires-Dist: numpy ==2.0.0
Requires-Dist: openai ==1.34.0
Requires-Dist: tqdm ==4.66.4
Requires-Dist: datasets ==2.20.0
Requires-Dist: matplotlib ==3.9.0
